{"cameraMode":{"drawMode":0,"name":"Shaded","section":"Shading Mode"},"sceneLighting":true,"audioPlay":false,"sceneViewState":{"m_AlwaysRefresh":false,"showFog":true,"showSkybox":true,"showFlares":true,"showImageEffects":true,"showParticleSystems":true,"showVisualEffectGraphs":true,"m_FxEnabled":true},"in2DMode":false,"pivot":{"x":29.299999237060548,"y":0.0,"z":-0.8999999761581421},"rotation":{"x":0.007537687197327614,"y":0.8375818133354187,"z":-0.5461389422416687,"w":0.011560160666704178},"size":7.497873306274414,"orthographic":false}